setup.cfg
setup.py
figplotter/__init__.py
figplotter/utils.py
figplotter.egg-info/PKG-INFO
figplotter.egg-info/SOURCES.txt
figplotter.egg-info/dependency_links.txt
figplotter.egg-info/entry_points.txt
figplotter.egg-info/requires.txt
figplotter.egg-info/top_level.txt
figplotter/plot/__init__.py
figplotter/plot/defaults.py
figplotter/plot/info.py
figplotter/plot/plot.py
figplotter/plot/plotter.py
figplotter/plot/style.py